<?xml version="1.0" encoding="windows-1252" ?>
<!DOCTYPE ViewObject SYSTEM "jbo_03_01.dtd">
<!---->
<ViewObject
  xmlns="http://xmlns.oracle.com/bc4j"
  Name="AllSalesRepLovVO"
  Version="12.2.1.22.48"
  InheritPersonalization="merge"
  BindingStyle="OracleName"
  CustomQuery="true"
  ComponentClass="model.lov.AllSalesRepLovVOImpl"
  PageIterMode="Full">
  <DesignTime>
    <Attr Name="_codeGenFlag2" Value="Coll"/>
    <Attr Name="_isExpertMode" Value="true"/>
  </DesignTime>
  <SQLQuery><![CDATA[select RESOURCE_SALESREP_ID party_id, party_name, party_number from XXFI_SALESPERSONS_T   
where status = 'A' AND sysdate between start_date_active and END_DATE_ACTIVE]]></SQLQuery>
  <ViewAttribute
    Name="PartyId"
    IsUpdateable="false"
    IsPersistent="false"
    PrecisionRule="true"
    Type="oracle.jbo.domain.Number"
    ColumnType="NUMBER"
    AliasName="PARTY_ID"
    Expression="PARTY_ID"
    SQLType="NUMERIC"/>
  <ViewAttribute
    Name="PartyName"
    IsUpdateable="false"
    IsPersistent="false"
    PrecisionRule="true"
    Precision="240"
    Type="java.lang.String"
    ColumnType="VARCHAR2"
    AliasName="PARTY_NAME"
    Expression="PARTY_NAME"
    SQLType="VARCHAR">
    <DesignTime>
      <Attr Name="_DisplaySize" Value="240"/>
    </DesignTime>
    <Properties>
      <SchemaBasedProperties>
        <LABEL
          ResId="SALES_PERSON"/>
        <DISPLAYWIDTH
          Value="30"/>
      </SchemaBasedProperties>
    </Properties>
  </ViewAttribute>
  <ViewAttribute
    Name="PartyNumber"
    IsUpdateable="false"
    IsPersistent="false"
    PrecisionRule="true"
    Precision="100"
    Type="java.lang.String"
    ColumnType="VARCHAR2"
    AliasName="PARTY_NUMBER"
    Expression="PARTY_NUMBER"
    SQLType="VARCHAR">
    <DesignTime>
      <Attr Name="_DisplaySize" Value="100"/>
    </DesignTime>
  </ViewAttribute>
  <ViewCriteria
    Name="AllSalesRepLovVOCriteria"
    ViewObjectName="model.lov.AllSalesRepLovVO"
    Conjunction="AND">
    <Properties Name="_Props">
      <CustomProperties>
        <Property
          Name="autoExecute"
          Value="false"/>
        <Property
          Name="mode"
          Value="Basic"/>
        <Property
          Name="allowConjunctionOverride"
          Value="true"/>
        <Property
          Name="showInList"
          Value="true"/>
        <Property
          Name="displayOperators"
          Value="InAdvancedMode"/>
      </CustomProperties>
    </Properties>
    <ViewCriteriaRow
      Name="AllSalesRepLovVOCriteria_row_0"
      UpperColumns="1">
      <ViewCriteriaItem
        Name="PartyName"
        ViewAttribute="PartyName"
        Operator="STARTSWITH"
        Conjunction="AND"
        Required="Optional"/>
    </ViewCriteriaRow>
  </ViewCriteria>
  <AttrArray Name="KeyAttributes">
    <Item Value="PartyId"/>
  </AttrArray>
  <ResourceBundle>
    <PropertiesBundle
      PropertiesFile="model.ADSModelBundle"/>
  </ResourceBundle>
</ViewObject>
